{"assets":{"AE6A67850A4857431B00E0EAB91FE92B":{"type":"texture","index":0,"assetRequest":{"type":"slide","state":"contents","slide":"none"},"url":{"native":"assets\/995BC729-4EE8-4A74-881A-F272E8A0BAAA.pdf"},"width":720,"height":405},"EE59F727DE1A954BAB84917CF404DB1F":{"type":"texture","index":1,"assetRequest":{"type":"slide","state":"contents","slide":"none"},"url":{"native":"assets\/995BC729-4EE8-4A74-881A-F272E8A0BAAA.pdf"},"width":720,"height":405}},"events":[{"effects":[{"beginTime":0,"baseLayer":{"animations":[],"initialState":{"affineTransform":[1,0,0,1,0,0],"masksToBounds":false,"rotation":0,"scale":1,"position":{"pointX":360,"pointY":202.5},"width":720,"sublayerTransform":[1,0,0,0,0,1,0,0,0,0,1,0,0,0,0,1],"contentsRect":{"y":0,"x":0,"width":1,"height":1},"opacity":1,"edgeAntialiasingMask":251658240,"height":405,"hidden":false,"anchorPoint":{"pointX":0.5,"pointY":0.5}},"objectID":"0","layers":[{"animations":[],"initialState":{"affineTransform":[1,0,0,1,0,0],"masksToBounds":false,"rotation":0,"scale":1,"position":{"pointX":360,"pointY":202.5},"width":720,"sublayerTransform":[1,0,0,0,0,1,0,0,0,0,1,-0.00093354433244735948,0,0,0,1],"contentsRect":{"y":0,"x":0,"width":1,"height":1},"opacity":1,"edgeAntialiasingMask":251658240,"height":405,"hidden":false,"anchorPoint":{"pointX":0.5,"pointY":0.5}},"layers":[{"animations":[],"layers":[],"texturedRectangle":{"isBackgroundTexture":false,"singleTextureOpacity":1,"textureType":0,"textBaseline":0,"textXHeight":0,"isVerticalText":false},"initialState":{"affineTransform":[1,0,0,1,0,0],"masksToBounds":false,"rotation":0,"scale":1,"position":{"pointX":360,"pointY":202.5},"width":720,"sublayerTransform":[1,0,0,0,0,1,0,0,0,0,1,0,0,0,0,1],"contentsRect":{"y":0,"x":0,"width":1,"height":1},"opacity":1,"edgeAntialiasingMask":0,"height":405,"hidden":false,"anchorPoint":{"pointX":0.5,"pointY":0.5}},"texture":"EE59F727DE1A954BAB84917CF404DB1F"},{"animations":[{"timeOffset":0,"from":{"scalar":false},"beginTime":0,"repeatCount":0,"fillMode":"both","property":"hidden","autoreverses":false,"duration":0.01,"to":{"scalar":true}}],"layers":[],"texturedRectangle":{"isBackgroundTexture":false,"singleTextureOpacity":1,"textureType":0,"textBaseline":0,"textXHeight":0,"isVerticalText":false},"initialState":{"affineTransform":[1,0,0,1,0,0],"masksToBounds":false,"rotation":0,"scale":1,"position":{"pointX":360,"pointY":202.5},"width":720,"sublayerTransform":[1,0,0,0,0,1,0,0,0,0,1,0,0,0,0,1],"contentsRect":{"y":0,"x":0,"width":1,"height":1},"opacity":1,"edgeAntialiasingMask":0,"height":405,"hidden":false,"anchorPoint":{"pointX":0.5,"pointY":0.5}},"texture":"AE6A67850A4857431B00E0EAB91FE92B"}]}]},"effects":[],"duration":0.01,"type":"transition","attributes":{"direction":0},"name":"none","objectID":"0"}],"automaticPlay":false,"hyperlinks":[],"accessibility":[{"text":"Nothing new, at this stage we’re just extending what we have","targetRectangle":{"y":296.28576040267944,"x":427.31621694564819,"width":212.44600000000003,"height":32}},{"text":"Going further","targetRectangle":{"y":15.40504789352417,"x":231.37734365463257,"width":271.04600051915645,"height":40}},{"text":"Daytime scene —-> Night time","targetRectangle":{"y":101.91335439682007,"x":432.68047475814819,"width":200.62900000000013,"height":16}},{"text":"Duplicate the original and modify the new.","targetRectangle":{"y":144.31603384017944,"x":72.155519008636475,"width":273.80800000000005,"height":38}},{"text":"If you are happy, then I highly recommend forking and going again, it could get messy","targetRectangle":{"y":201.31603384017944,"x":72.155519008636475,"width":252.43199999999996,"height":57}},{"text":"Screenshot 2019-11-16 at 11.10.18.png","targetRectangle":{"y":-65.765625,"x":366.1287260636168,"width":309.375,"height":536.52923159417696}},{"text":"Iterate","targetRectangle":{"y":336.19109487533569,"x":195.9409943819046,"width":77.249999862313302,"height":24}}],"baseLayer":{"animations":[],"initialState":{"affineTransform":[1,0,0,1,0,0],"masksToBounds":false,"rotation":0,"scale":1,"position":{"pointX":360,"pointY":202.5},"width":720,"sublayerTransform":[1,0,0,0,0,1,0,0,0,0,1,0,0,0,0,1],"contentsRect":{"y":0,"x":0,"width":1,"height":1},"opacity":1,"edgeAntialiasingMask":251658240,"height":405,"hidden":false,"anchorPoint":{"pointX":0.5,"pointY":0.5}},"objectID":"0","layers":[{"animations":[],"initialState":{"affineTransform":[1,0,0,1,0,0],"masksToBounds":false,"rotation":0,"scale":1,"position":{"pointX":360,"pointY":202.5},"width":720,"sublayerTransform":[1,0,0,0,0,1,0,0,0,0,1,-0.00093354433244735948,0,0,0,1],"contentsRect":{"y":0,"x":0,"width":1,"height":1},"opacity":1,"edgeAntialiasingMask":251658240,"height":405,"hidden":false,"anchorPoint":{"pointX":0.5,"pointY":0.5}},"layers":[{"animations":[],"layers":[],"texturedRectangle":{"isBackgroundTexture":false,"singleTextureOpacity":1,"textureType":0,"textBaseline":0,"textXHeight":0,"isVerticalText":false},"initialState":{"affineTransform":[1,0,0,1,0,0],"masksToBounds":false,"rotation":0,"scale":1,"position":{"pointX":360,"pointY":202.5},"width":720,"sublayerTransform":[1,0,0,0,0,1,0,0,0,0,1,0,0,0,0,1],"contentsRect":{"y":0,"x":0,"width":1,"height":1},"opacity":1,"edgeAntialiasingMask":0,"height":405,"hidden":false,"anchorPoint":{"pointX":0.5,"pointY":0.5}},"texture":"AE6A67850A4857431B00E0EAB91FE92B"}]}]}}]}